imgzen/__init__.py
imgzen/main.py
imgzen/utils.py
imgzen-0.1.2.dist-info/METADATA
imgzen-0.1.2.dist-info/WHEEL
imgzen-0.1.2.dist-info/entry_points.txt
imgzen-0.1.2.dist-info/top_level.txt
imgzen-0.1.2.dist-info/RECORD
